medialink/__init__.py
medialink/cli.py
medialink/generate.py
medialink/main.py
medialink/media_classes.py
medialink/messages.py
medialink/options.py
medialink/scan.py
medialink/videoformats.txt
medialink-0.1.3.dist-info/LICENSE
medialink-0.1.3.dist-info/METADATA
medialink-0.1.3.dist-info/WHEEL
medialink-0.1.3.dist-info/entry_points.txt
medialink-0.1.3.dist-info/RECORD
