Metadata-Version: 2.1
Name: medialink
Version: 0.1.3
Summary: Medialink is a Python CLI-tool for bringing order to your digital film and tv-show library.
Author: Josef Anhede
Author-email: josefanhede@gmail.com
Requires-Python: >=3.10,<4.0
Classifier: Programming Language :: Python :: 3
Classifier: Programming Language :: Python :: 3.10
Classifier: Programming Language :: Python :: 3.11
Classifier: Programming Language :: Python :: 3.12
Classifier: Programming Language :: Python :: 3.13
Requires-Dist: click (>=8.1.7,<9.0.0)
Requires-Dist: guessit (>=3.8.0,<4.0.0)
Requires-Dist: mypy (>=1.13.0,<2.0.0)
Requires-Dist: ruff (>=0.7.1,<0.8.0)
